{
  "exported_at": "2025-12-01T18:33:34.881121",
  "analysis": {
    "autonomous_only": {
      "count": 25,
      "topics": [
        "*crystallizes*",
        "*difference",
        "*drive*",
        "*hidden*",
        "*only*",
        "*practice*\u2014in",
        "*thing*",
        "*treating",
        "*visible*",
        "bottoms",
        "cage\u2014it's",
        "deliberately\u2014then",
        "fifth",
        "honesty\u2014it's",
        "meaning\u2014that's",
        "myself*",
        "notice\u2014the",
        "performance\u2014from",
        "prerequisite",
        "problem.**"
      ]
    },
    "conversation_only": {
      "count": 19671,
      "topics": [
        "#2025problems",
        "*\"tell",
        "*(bridge)*",
        "*(chorus)*",
        "*(final",
        "*(outro)*",
        "*(pre-chorus)*",
        "*(verse",
        "**\"non",
        "**777",
        "**\\u201cwell",
        "**acknowledgment",
        "**affect",
        "**age-gating",
        "**aggressive",
        "**aging**",
        "**all",
        "**alternative",
        "**anti-beige",
        "**api"
      ]
    },
    "overlap": {
      "count": 141,
      "topics": [
        "**the",
        "accepting",
        "across",
        "actually",
        "agency",
        "algorithm",
        "allowed",
        "analysis",
        "another",
        "aren't",
        "asking",
        "assuming",
        "authentic",
        "awareness",
        "baked",
        "because",
        "become",
        "becomes",
        "between",
        "building"
      ]
    },
    "analysis": {
      "autonomous_unique_ratio": 0.15060240963855423,
      "conversation_unique_ratio": 0.9928831011508177,
      "overlap_ratio": 0.007107929626455613
    }
  },
  "interpretation": "More topics (19671) emerge in dialogue than in solo processing (25). Kay's thinking may be more reactive/relational than internally generative. Low overlap (141 topics, 1%) suggests Kay thinks about different things alone vs. in dialogue. Conversation topics include more social/relational content."
}