{
  "doc_id": "doc_1762382777",
  "title": "Test-gerbils.txt",
  "shape_description": "Document with 5 peripheral",
  "access_count": 0,
  "last_accessed": null,
  "branches": [
    {
      "title": "Context & Details",
      "chunk_indices": [
        0,
        1,
        2,
        3,
        4
      ],
      "glyphs": "\ud83d\udcdd",
      "access_tier": "cold",
      "access_count": 0,
      "last_accessed": null
    }
  ],
  "total_chunks": 5,
  "created_at": "2025-11-05T17:46:34.255015"
}